{
  "hymn_number": 293,
  "title": "Himi 293",
  "hymnal": "thb",
  "lyrics": [
    {
      "page_name": "Verse 1",
      "text": "’Oku Kingi ‘a Sihova,\nKe tau fakafeta’i;\nKo hotau ‘Otua ia,\n‘Oku tau lelei ai."
    },
    {
      "page_name": "Verse 2",
      "text": "Fakafeta’i, ki he Tamai,\n‘I he’ene ‘ofa,\nKi he kakai tu’utāmaki,\n‘I he’etau hia."
    },
    {
      "page_name": "Verse 3",
      "text": "’O ne filio’i poto,\nKia kitautolu,\nMo ne kumi ‘a e hifo,\n‘Oku mahuinga."
    },
    {
      "page_name": "Verse 4",
      "text": "Fakafeta’i ki he ‘Alo,\n‘I he’ene ‘ofa,\nMo ‘ene fa’a ‘aofia\nHotau laumālie."
    },
    {
      "page_name": "Verse 5",
      "text": "Pea ke tau fakafeta’i,\nKi he Laumālie;\n‘I he’ene langaki mai,\n‘A ‘etua mo’ui."
    }
  ],
  "author": "",
  "composer": "",
  "tune_name": "",
  "text_copyright": "",
  "tune_copyright": ""
}