{
  "hymn_number": 36,
  "title": "Himi 36",
  "hymnal": "thb",
  "lyrics": [
    {
      "page_name": "Verse 1",
      "text": "’Eiki ko homau ‘Otua\nKo homau tokoni,\nKo homau falala’anga\nKe mau mo’ui ai."
    },
    {
      "page_name": "Verse 2",
      "text": "Ko e unga’anga Koe\nKi he āfangia,\nKo e iku’anga Koe\nKi he kau fononga."
    },
    {
      "page_name": "Verse 3",
      "text": "’Ofa ke mau nofo ma’u pē\nKi he ‘Afiona,\nKo e unga’anga lelei\nPea ta’engata."
    },
    {
      "page_name": "Verse 4",
      "text": "’I he te’eki fokotu’u\n‘A e ngaahi mo’unga,\nKo e ‘Otua pē Koe\nPea fai ma’u ai pē."
    },
    {
      "page_name": "Verse 5",
      "text": "Ko e ngaahi ta’u ‘e afe\n‘Oku ‘i ho ‘ao\nHangē ko e pō pe taha\nKuo toki ‘alu."
    },
    {
      "page_name": "Verse 6",
      "text": "’Eiki ke ke kei tokoni\nKi ho kakai vaivai,\nPea malu’i ma’u ai pē\nHomau laumālie"
    }
  ],
  "author": "",
  "composer": "",
  "tune_name": "",
  "text_copyright": "",
  "tune_copyright": ""
}