{
  "hymn_number": 517,
  "title": "Himi 517",
  "hymnal": "thb",
  "lyrics": [
    {
      "page_name": "Verse 1",
      "text": "‘E ‘Eiki ‘omi kia au\n‘A e anga fakama’uma’u;\n‘A e loto ala ke momoi\nMounu ‘a e Toko Taha kovi."
    },
    {
      "page_name": "Verse 2",
      "text": "Ko e fefa’uhi ‘oku fai,\nFekuki mo ha’a fakalangi;\nHe ngaahi matatau ne tō\nMei he tu’unga ‘āngelo."
    },
    {
      "page_name": "Verse 3",
      "text": "‘Oku nau kei malohi fau,\n‘Atamai ‘oku hulu atu,\nPotopoto’i he pō kakai,\n‘Asili ko e maheni ai."
    },
    {
      "page_name": "Verse 4",
      "text": "‘Oku nau mounu ‘a e tauhele\nHa taha hoku anga pele;\nNgaūe ‘a e fatu ni ke kai\nNeongo te te mate ai."
    },
    {
      "page_name": "Verse 5",
      "text": "‘Io ko e faito’o pē ‘e lava\nKo e taa’i hoto ‘ofa’anga;\nHele ‘a e uho ‘o e holi,\nTatau mo hoto fakapoongi."
    },
    {
      "page_name": "Verse 6",
      "text": "‘Eiki, ko koe pe ‘e lava;\nHā’ele mai ni, pea tafa;\nTa’aki fu’u mo hono aka,\nKau nofo mo e loto ma’a."
    }
  ],
  "author": "",
  "composer": "",
  "tune_name": "",
  "text_copyright": "",
  "tune_copyright": ""
}