{
  "hymn_number": 145,
  "title": "Himi 145",
  "hymnal": "thb",
  "author": "",
  "composer": "",
  "tune_name": "",
  "text_copyright": "",
  "tune_copyright": "",
  "lyrics": "M.N.N.\n1.\nSīsū ‘Afio mai\nKi he’eku vaivai,\nPea fakaakake\nHo’o ngāue lelei.\n2.\nPea u loto feinga\nKi hoku ‘Otua,\nPea u fai velenga ma’u pē\nKi he ‘Afiona.\n3.\nPea u loto ‘ofa,\nKi he ‘alu mālie\n‘O e kakai kotoa pē\n‘Oku tu’utāmaki.\n4.\nKe nofo’ia au\n‘E ho Laumālie\nKe ne fakaloto’i au,\nKi he ‘Afiona.\n5.\nPea ke hoko ai,\nHoku loto vela;\nKo e ‘ofa angatonu,\nPea mo’onia. *"
}