{
  "hymn_number": 247,
  "title": "Himi 247",
  "hymnal": "thb",
  "author": "",
  "composer": "",
  "tune_name": "",
  "text_copyright": "",
  "tune_copyright": "",
  "lyrics": "M.L.\n1.\nKo Sihova ko e ‘Eiki\n‘O e langi mo māmani;\n‘Oku fai mā’oni’oni,\nKi he kakai kotoa pē.\n2.\nKo hotau ‘Otua ia,\nKe tau manavahē ki ai\nKo hotau mo’ui’anga,\nKe tau fa’a kumi ki ai.\n3.\nPea ‘oku māfimafi,\n‘A e Eiki, ko Sihova;\n‘Oku pule fai ma’u ai pē,\nKi he me’a kotoa pē.\n4.\nKe fai fakafeta’i ma’u pē,\nKi he ‘Otua mo’oni\n‘E he kakai kotoa pē,\n‘Oku nofo ‘i māmani. *"
}