{
  "hymn_number": 491,
  "title": "Himi 491",
  "hymnal": "thb",
  "author": "",
  "composer": "",
  "tune_name": "",
  "text_copyright": "",
  "tune_copyright": "",
  "lyrics": "M.L.\n(Ko Siope 19:25)\n1.\n‘Oku mo’ui hoku ‘Eiki,\n‘Oku ou ‘ilo pau ki ai;\nPea ka hoko hono taimi\nTe Ne hā’ele ki māmani.\n2.\nPea neongo ‘oku mohe\nHoku kakano ‘i fa’itoka,\nEfu ‘a e sino ni, ‘o mole;\nKa teu mātā hono fofonga.\n3.\nMātā ‘e hoku mata ni,\n‘O ‘ikai ha taha kehe,\n‘O sio hono langilangi\n‘E au naʻe koto kelekele.\n4.\n‘Oku ou fu’u ongo’i ē\n‘A e ivi te u mo’ui ai;\n‘Afio mai ‘a e Laumālie\nKo hoku faka’amanak\ni\n.\n5.\nToki fo’ou pe ‘a e mo’ui,\nMole ‘a e kovi fulipē;\nPea kakato ‘a e huhu’i\nHe sino, loto, laumālie.*"
}