{
  "hymn_number": 529,
  "title": "Himi 529",
  "hymnal": "thb",
  "author": "",
  "composer": "",
  "tune_name": "",
  "text_copyright": "",
  "tune_copyright": "",
  "lyrics": "8.7.8.7.& tau\n(Ko ‘Aisea 49:2)\n1.\nKa matangi ‘o peaua\nTahi he mo’ui ia,\nTe u hūfanga he ‘Otua,\n‘I he malu hono nima.\nTe Ne fufū au,\nTe Ne fufū hono ‘aofinima.\n2.\nTe Ne tuku ke u mamahi,\nTe Ne kiʻi kinisi nai;\nKo e ‘ofa kuo lahi,\n‘Ofa faka’etamai.\nTe Ne fufū au\nTe Ne fufū hono ‘aofinima.\n3.\nFeinga hoku ngaahi fili,\nTōtōivi ‘a Sētane;\nKae liliu pē ‘e he ‘Eiki\nKe lelei kotoa pē.\nTe Ne fufū au\nTe Ne fufū hono ‘aofinima.\n4.\nLolotonga ‘eku fua\nHe kolosi kuo hili,\nMamahi’i au he ‘Otua,\nTauhi ‘ene tamasi’i.\nTe Ne fufū au\nTe Ne fufū hono ‘aofinima.*"
}