{
  "hymn_number": 615,
  "title": "Himi 615",
  "hymnal": "thb",
  "author": "",
  "composer": "",
  "tune_name": "",
  "text_copyright": "",
  "tune_copyright": "",
  "lyrics": "M.L.\n(“Ka na’e tu’u mei he mama’o\nhono kau fe’iloaki kotoa pē ...\n‘o nau mamata.”)\n1.\nHa’u, ke tau nofo hifo ē,\n‘O hanga hake he ‘Akau na!\nFanongo ki heʻene toʻe!\nHia ‘atautolu ‘oku fua.\n2.\nKoloto ke tau fākafoa,\n‘O tangi lo’imata mu’a,\nHe sio ki heʻene ‘ofa.\nHia ‘atautolu ʻoku fua!\n3.\nFanongo hono manukia\n‘E he hou’eiki mo e tu’a!\nNe Ne kātaki fēfē Ia?\nHia ‘atautolu oku fua!\n4.\nMo’oni pē ‘a ‘enau lau,\n“Ka ko e ‘Alo he ‘Otua,\nKuo Ne hifo he ‘Akau” -\nHia ‘atautolu ‘oku fua!\n5.\nHono mapuke ‘e he fa’o\n‘A e ‘Eiki Lahi ‘o Natula?\nKa na’a Ne sio he mamaʻo,\nHia ‘atautolu ‘oku fua!\n6.\nFai hono loto’i tangata\nKe tō pē ki he faingofua:\nKae lava fēfē hono ngafa?\nHia ‘atautolu ‘oku fua.\n7.\nFekuki fakaofo ia,\n‘A e tau ‘a e ‘ofa ‘a e ‘Otua\nKe tamate’i ‘a e malaʻia.\nHia ‘atautolu ‘oku fua.\n8.\nFakafeta’i ne fai ke lava,\nPea ko ‘ofa na’e ikuna.\n‘Oku ‘atā ni ‘a e Tangata.\nHia ‘atautolu KUO fua. *"
}