{
  "book": "ISA",
  "book_name": "Isaiah",
  "chapter": 3,
  "version_id": 3523,
  "url": "https://www.bible.com/bible/3523/ISA.3",
  "verses": [
    {
      "verse": 1,
      "text": "For now the Sovereign, the Lord of hosts, is taking away from Jerusalem and from Judah support and staff— all support of bread and all support of water—"
    },
    {
      "verse": 2,
      "text": "warrior and soldier, judge and prophet, diviner and elder,"
    },
    {
      "verse": 3,
      "text": "captain of fifty and dignitary, counselor and skillful magician and expert enchanter."
    },
    {
      "verse": 4,
      "text": "And I will make youths their princes, and children shall rule over them."
    },
    {
      "verse": 5,
      "text": "The people will be oppressed, everyone by another and everyone by a neighbor; the youth will be insolent to the elder and the base to the honorable."
    },
    {
      "verse": 6,
      "text": "Someone will seize a relative, a member of the clan, saying, “You have a cloak; you shall be our leader, and this heap of ruins shall be under your rule.”"
    },
    {
      "verse": 7,
      "text": "But the other will cry out on that day, saying, “I will not be a healer; in my house there is neither bread nor cloak; you shall not make me leader of the people.”"
    },
    {
      "verse": 8,
      "text": "For Jerusalem has stumbled, and Judah has fallen, because their speech and their deeds are against the Lord, defying his glorious presence."
    },
    {
      "verse": 9,
      "text": "The look on their faces bears witness against them; they proclaim their sin like Sodom; they do not hide it. Woe to them, for they have brought evil on themselves."
    },
    {
      "verse": 10,
      "text": "Tell the innocent how fortunate they are, for they shall eat the fruit of their labors."
    },
    {
      "verse": 11,
      "text": "Woe to the guilty! How unfortunate they are, for what their hands have done shall be done to them."
    },
    {
      "verse": 12,
      "text": "My people—their oppressors extort them, and creditors rule over them. O my people, your leaders mislead you and confuse the course of your paths."
    },
    {
      "verse": 13,
      "text": "The Lord rises to argue his case; he stands to judge the peoples."
    },
    {
      "verse": 14,
      "text": "The Lord enters into judgment with the elders and princes of his people: It is you who have devoured the vineyard; the spoil of the poor is in your houses."
    },
    {
      "verse": 15,
      "text": "What do you mean by crushing my people, by grinding the face of the poor? says the Lord God of hosts."
    },
    {
      "verse": 16,
      "text": "The Lord said: Because the daughters of Zion are haughty and walk with outstretched necks, glancing wantonly with their eyes, mincing along as they go, tinkling with their feet;"
    },
    {
      "verse": 17,
      "text": "the Lord will afflict with scabs the heads of the daughters of Zion, and the Lord will lay bare their scalps and heads."
    },
    {
      "verse": 18,
      "text": "On that day the Lord will take away the finery of the anklets, the headbands, and the crescents;"
    },
    {
      "verse": 19,
      "text": "the pendants, the bracelets, and the scarfs;"
    },
    {
      "verse": 20,
      "text": "the headdresses, the armlets, the sashes, the perfume boxes, and the amulets;"
    },
    {
      "verse": 21,
      "text": "the signet rings and nose rings;"
    },
    {
      "verse": 22,
      "text": "the festal robes, the mantles, the cloaks, and the handbags;"
    },
    {
      "verse": 23,
      "text": "the garments of gauze, the linen garments, the turbans, and the veils."
    },
    {
      "verse": 24,
      "text": "Instead of perfume there will be a stench; and instead of a sash, a rope; and instead of well-styled hair, baldness; and instead of a rich robe, a binding of sackcloth; instead of beauty, shame."
    },
    {
      "verse": 25,
      "text": "Your men shall fall by the sword and your warriors in battle."
    },
    {
      "verse": 26,
      "text": "And her gates shall lament and mourn; desolate, she shall sit upon the ground."
    }
  ],
  "timestamp": "2025-08-08T15:50:22.757630"
}